c/flip.c
c/macros.c
c/main.c
c/readio.c
c/sample.c
optas/__init__.py
optas/construct.py
optas/divergences.py
optas/flip.py
optas/matrix.py
optas/opt.py
optas/orderm2
optas/packing.py
optas/phi
optas/sample.py
optas/tree.py
optas/utils.py
optas/version.py
optas/writeio.py
optas/examples/__init__.py
optas/examples/maxerror.py
optas/examples/sampling.py
optas/tests/__init__.py
optas/tests/test_divergences.py
optas/tests/test_matrix.py
optas/tests/test_opt.py
optas/tests/test_packing.py
optas/tests/test_sample.py
optas/tests/test_tree.py
optas/tests/test_utils.py
optas/tests/utils.py
optas-1.0.3.dist-info/LICENSE.txt
optas-1.0.3.dist-info/METADATA
optas-1.0.3.dist-info/WHEEL
optas-1.0.3.dist-info/top_level.txt
optas-1.0.3.dist-info/RECORD
