Metadata-Version: 2.1
Name: optas
Version: 1.0.3
Summary: Optimal Approximate Sampling from Discrete Probability Distributions
Home-page: https://github.com/probcomp/optimal-approximate-sampling
Maintainer: Feras A. Saad
Maintainer-email: fsaad@mit.edu
License: Apache-2.0
Platform: UNKNOWN
Classifier: Development Status :: 2 - Pre-Alpha
Classifier: Intended Audience :: Science/Research
Classifier: License :: OSI Approved :: Apache Software License
Classifier: Programming Language :: Python :: 3
Provides-Extra: tests
Requires-Dist: pytest ; extra == 'tests'
Requires-Dist: scipy ; extra == 'tests'
